{
  "_format": "hh-sol-cache-2",
  "files": {
    "/home/runner/work/solidity-notebook/solidity-notebook/contracts/crud/DataStorage_1768085982.sol": {
      "lastModificationDate": 1768087978234,
      "contentHash": "73472ce8128177f3b1dad2fc29523081",
      "sourceName": "contracts/crud/DataStorage_1768085982.sol",
      "solcConfig": {
        "version": "0.8.24",
        "settings": {
          "optimizer": {
            "enabled": true,
            "runs": 200
          },
          "evmVersion": "paris",
          "outputSelection": {
            "*": {
              "*": [
                "abi",
                "evm.bytecode",
                "evm.deployedBytecode",
                "evm.methodIdentifiers",
                "metadata"
              ],
              "": [
                "ast"
              ]
            }
          }
        }
      },
      "imports": [],
      "versionPragmas": [
        "^0.8.24"
      ],
      "artifacts": [
        "DataStorage"
      ]
    },
    "/home/runner/work/solidity-notebook/solidity-notebook/contracts/crud/Handler_1768085636.sol": {
      "lastModificationDate": 1768087978234,
      "contentHash": "29c5392cf349720fe45d3649a14c01c5",
      "sourceName": "contracts/crud/Handler_1768085636.sol",
      "solcConfig": {
        "version": "0.8.24",
        "settings": {
          "optimizer": {
            "enabled": true,
            "runs": 200
          },
          "evmVersion": "paris",
          "outputSelection": {
            "*": {
              "*": [
                "abi",
                "evm.bytecode",
                "evm.deployedBytecode",
                "evm.methodIdentifiers",
                "metadata"
              ],
              "": [
                "ast"
              ]
            }
          }
        }
      },
      "imports": [],
      "versionPragmas": [
        "^0.8.24"
      ],
      "artifacts": [
        "Handler_1768085636"
      ]
    },
    "/home/runner/work/solidity-notebook/solidity-notebook/contracts/security/AccessControl_1767900995.sol": {
      "lastModificationDate": 1768087978235,
      "contentHash": "0eaa5305a95fb8e5fcf5f52721f44b8b",
      "sourceName": "contracts/security/AccessControl_1767900995.sol",
      "solcConfig": {
        "version": "0.8.24",
        "settings": {
          "optimizer": {
            "enabled": true,
            "runs": 200
          },
          "evmVersion": "paris",
          "outputSelection": {
            "*": {
              "*": [
                "abi",
                "evm.bytecode",
                "evm.deployedBytecode",
                "evm.methodIdentifiers",
                "metadata"
              ],
              "": [
                "ast"
              ]
            }
          }
        }
      },
      "imports": [],
      "versionPragmas": [
        "^0.8.24"
      ],
      "artifacts": [
        "AccessControl"
      ]
    },
    "/home/runner/work/solidity-notebook/solidity-notebook/contracts/security/AccessControl_1767956151.sol": {
      "lastModificationDate": 1768087978235,
      "contentHash": "0eaa5305a95fb8e5fcf5f52721f44b8b",
      "sourceName": "contracts/security/AccessControl_1767956151.sol",
      "solcConfig": {
        "version": "0.8.24",
        "settings": {
          "optimizer": {
            "enabled": true,
            "runs": 200
          },
          "evmVersion": "paris",
          "outputSelection": {
            "*": {
              "*": [
                "abi",
                "evm.bytecode",
                "evm.deployedBytecode",
                "evm.methodIdentifiers",
                "metadata"
              ],
              "": [
                "ast"
              ]
            }
          }
        }
      },
      "imports": [],
      "versionPragmas": [
        "^0.8.24"
      ],
      "artifacts": [
        "AccessControl"
      ]
    },
    "/home/runner/work/solidity-notebook/solidity-notebook/contracts/security/AccessControl_1768038425.sol": {
      "lastModificationDate": 1768087978235,
      "contentHash": "0eaa5305a95fb8e5fcf5f52721f44b8b",
      "sourceName": "contracts/security/AccessControl_1768038425.sol",
      "solcConfig": {
        "version": "0.8.24",
        "settings": {
          "optimizer": {
            "enabled": true,
            "runs": 200
          },
          "evmVersion": "paris",
          "outputSelection": {
            "*": {
              "*": [
                "abi",
                "evm.bytecode",
                "evm.deployedBytecode",
                "evm.methodIdentifiers",
                "metadata"
              ],
              "": [
                "ast"
              ]
            }
          }
        }
      },
      "imports": [],
      "versionPragmas": [
        "^0.8.24"
      ],
      "artifacts": [
        "AccessControl"
      ]
    },
    "/home/runner/work/solidity-notebook/solidity-notebook/contracts/security/AccessControl_1768041579.sol": {
      "lastModificationDate": 1768087978235,
      "contentHash": "0eaa5305a95fb8e5fcf5f52721f44b8b",
      "sourceName": "contracts/security/AccessControl_1768041579.sol",
      "solcConfig": {
        "version": "0.8.24",
        "settings": {
          "optimizer": {
            "enabled": true,
            "runs": 200
          },
          "evmVersion": "paris",
          "outputSelection": {
            "*": {
              "*": [
                "abi",
                "evm.bytecode",
                "evm.deployedBytecode",
                "evm.methodIdentifiers",
                "metadata"
              ],
              "": [
                "ast"
              ]
            }
          }
        }
      },
      "imports": [],
      "versionPragmas": [
        "^0.8.24"
      ],
      "artifacts": [
        "AccessControl"
      ]
    },
    "/home/runner/work/solidity-notebook/solidity-notebook/contracts/security/AccessControl_1768081932.sol": {
      "lastModificationDate": 1768087978235,
      "contentHash": "0eaa5305a95fb8e5fcf5f52721f44b8b",
      "sourceName": "contracts/security/AccessControl_1768081932.sol",
      "solcConfig": {
        "version": "0.8.24",
        "settings": {
          "optimizer": {
            "enabled": true,
            "runs": 200
          },
          "evmVersion": "paris",
          "outputSelection": {
            "*": {
              "*": [
                "abi",
                "evm.bytecode",
                "evm.deployedBytecode",
                "evm.methodIdentifiers",
                "metadata"
              ],
              "": [
                "ast"
              ]
            }
          }
        }
      },
      "imports": [],
      "versionPragmas": [
        "^0.8.24"
      ],
      "artifacts": [
        "AccessControl"
      ]
    },
    "/home/runner/work/solidity-notebook/solidity-notebook/contracts/utils/Analytics_1767859051.sol": {
      "lastModificationDate": 1768087978235,
      "contentHash": "258af6e808cc37429a1a33202bad7d93",
      "sourceName": "contracts/utils/Analytics_1767859051.sol",
      "solcConfig": {
        "version": "0.8.24",
        "settings": {
          "optimizer": {
            "enabled": true,
            "runs": 200
          },
          "evmVersion": "paris",
          "outputSelection": {
            "*": {
              "*": [
                "abi",
                "evm.bytecode",
                "evm.deployedBytecode",
                "evm.methodIdentifiers",
                "metadata"
              ],
              "": [
                "ast"
              ]
            }
          }
        }
      },
      "imports": [],
      "versionPragmas": [
        "^0.8.24"
      ],
      "artifacts": [
        "Analytics"
      ]
    },
    "/home/runner/work/solidity-notebook/solidity-notebook/contracts/utils/Analytics_1767880521.sol": {
      "lastModificationDate": 1768087978235,
      "contentHash": "258af6e808cc37429a1a33202bad7d93",
      "sourceName": "contracts/utils/Analytics_1767880521.sol",
      "solcConfig": {
        "version": "0.8.24",
        "settings": {
          "optimizer": {
            "enabled": true,
            "runs": 200
          },
          "evmVersion": "paris",
          "outputSelection": {
            "*": {
              "*": [
                "abi",
                "evm.bytecode",
                "evm.deployedBytecode",
                "evm.methodIdentifiers",
                "metadata"
              ],
              "": [
                "ast"
              ]
            }
          }
        }
      },
      "imports": [],
      "versionPragmas": [
        "^0.8.24"
      ],
      "artifacts": [
        "Analytics"
      ]
    },
    "/home/runner/work/solidity-notebook/solidity-notebook/contracts/utils/Analytics_1767895032.sol": {
      "lastModificationDate": 1768087978235,
      "contentHash": "258af6e808cc37429a1a33202bad7d93",
      "sourceName": "contracts/utils/Analytics_1767895032.sol",
      "solcConfig": {
        "version": "0.8.24",
        "settings": {
          "optimizer": {
            "enabled": true,
            "runs": 200
          },
          "evmVersion": "paris",
          "outputSelection": {
            "*": {
              "*": [
                "abi",
                "evm.bytecode",
                "evm.deployedBytecode",
                "evm.methodIdentifiers",
                "metadata"
              ],
              "": [
                "ast"
              ]
            }
          }
        }
      },
      "imports": [],
      "versionPragmas": [
        "^0.8.24"
      ],
      "artifacts": [
        "Analytics"
      ]
    },
    "/home/runner/work/solidity-notebook/solidity-notebook/contracts/utils/Analytics_1767903697.sol": {
      "lastModificationDate": 1768087978235,
      "contentHash": "258af6e808cc37429a1a33202bad7d93",
      "sourceName": "contracts/utils/Analytics_1767903697.sol",
      "solcConfig": {
        "version": "0.8.24",
        "settings": {
          "optimizer": {
            "enabled": true,
            "runs": 200
          },
          "evmVersion": "paris",
          "outputSelection": {
            "*": {
              "*": [
                "abi",
                "evm.bytecode",
                "evm.deployedBytecode",
                "evm.methodIdentifiers",
                "metadata"
              ],
              "": [
                "ast"
              ]
            }
          }
        }
      },
      "imports": [],
      "versionPragmas": [
        "^0.8.24"
      ],
      "artifacts": [
        "Analytics"
      ]
    },
    "/home/runner/work/solidity-notebook/solidity-notebook/contracts/utils/Analytics_1767970732.sol": {
      "lastModificationDate": 1768087978235,
      "contentHash": "258af6e808cc37429a1a33202bad7d93",
      "sourceName": "contracts/utils/Analytics_1767970732.sol",
      "solcConfig": {
        "version": "0.8.24",
        "settings": {
          "optimizer": {
            "enabled": true,
            "runs": 200
          },
          "evmVersion": "paris",
          "outputSelection": {
            "*": {
              "*": [
                "abi",
                "evm.bytecode",
                "evm.deployedBytecode",
                "evm.methodIdentifiers",
                "metadata"
              ],
              "": [
                "ast"
              ]
            }
          }
        }
      },
      "imports": [],
      "versionPragmas": [
        "^0.8.24"
      ],
      "artifacts": [
        "Analytics"
      ]
    },
    "/home/runner/work/solidity-notebook/solidity-notebook/contracts/utils/Analytics_1768037877.sol": {
      "lastModificationDate": 1768087978235,
      "contentHash": "258af6e808cc37429a1a33202bad7d93",
      "sourceName": "contracts/utils/Analytics_1768037877.sol",
      "solcConfig": {
        "version": "0.8.24",
        "settings": {
          "optimizer": {
            "enabled": true,
            "runs": 200
          },
          "evmVersion": "paris",
          "outputSelection": {
            "*": {
              "*": [
                "abi",
                "evm.bytecode",
                "evm.deployedBytecode",
                "evm.methodIdentifiers",
                "metadata"
              ],
              "": [
                "ast"
              ]
            }
          }
        }
      },
      "imports": [],
      "versionPragmas": [
        "^0.8.24"
      ],
      "artifacts": [
        "Analytics"
      ]
    },
    "/home/runner/work/solidity-notebook/solidity-notebook/contracts/utils/Analytics_1768040332.sol": {
      "lastModificationDate": 1768087978235,
      "contentHash": "258af6e808cc37429a1a33202bad7d93",
      "sourceName": "contracts/utils/Analytics_1768040332.sol",
      "solcConfig": {
        "version": "0.8.24",
        "settings": {
          "optimizer": {
            "enabled": true,
            "runs": 200
          },
          "evmVersion": "paris",
          "outputSelection": {
            "*": {
              "*": [
                "abi",
                "evm.bytecode",
                "evm.deployedBytecode",
                "evm.methodIdentifiers",
                "metadata"
              ],
              "": [
                "ast"
              ]
            }
          }
        }
      },
      "imports": [],
      "versionPragmas": [
        "^0.8.24"
      ],
      "artifacts": [
        "Analytics"
      ]
    },
    "/home/runner/work/solidity-notebook/solidity-notebook/contracts/utils/Analytics_1768067467.sol": {
      "lastModificationDate": 1768087978235,
      "contentHash": "258af6e808cc37429a1a33202bad7d93",
      "sourceName": "contracts/utils/Analytics_1768067467.sol",
      "solcConfig": {
        "version": "0.8.24",
        "settings": {
          "optimizer": {
            "enabled": true,
            "runs": 200
          },
          "evmVersion": "paris",
          "outputSelection": {
            "*": {
              "*": [
                "abi",
                "evm.bytecode",
                "evm.deployedBytecode",
                "evm.methodIdentifiers",
                "metadata"
              ],
              "": [
                "ast"
              ]
            }
          }
        }
      },
      "imports": [],
      "versionPragmas": [
        "^0.8.24"
      ],
      "artifacts": [
        "Analytics"
      ]
    },
    "/home/runner/work/solidity-notebook/solidity-notebook/contracts/utils/Analytics_1768083335.sol": {
      "lastModificationDate": 1768087978235,
      "contentHash": "258af6e808cc37429a1a33202bad7d93",
      "sourceName": "contracts/utils/Analytics_1768083335.sol",
      "solcConfig": {
        "version": "0.8.24",
        "settings": {
          "optimizer": {
            "enabled": true,
            "runs": 200
          },
          "evmVersion": "paris",
          "outputSelection": {
            "*": {
              "*": [
                "abi",
                "evm.bytecode",
                "evm.deployedBytecode",
                "evm.methodIdentifiers",
                "metadata"
              ],
              "": [
                "ast"
              ]
            }
          }
        }
      },
      "imports": [],
      "versionPragmas": [
        "^0.8.24"
      ],
      "artifacts": [
        "Analytics"
      ]
    },
    "/home/runner/work/solidity-notebook/solidity-notebook/contracts/utils/EventLogger_1767828151.sol": {
      "lastModificationDate": 1768087978235,
      "contentHash": "261c7e8eced1c852b3ea6fd3f1bf851c",
      "sourceName": "contracts/utils/EventLogger_1767828151.sol",
      "solcConfig": {
        "version": "0.8.24",
        "settings": {
          "optimizer": {
            "enabled": true,
            "runs": 200
          },
          "evmVersion": "paris",
          "outputSelection": {
            "*": {
              "*": [
                "abi",
                "evm.bytecode",
                "evm.deployedBytecode",
                "evm.methodIdentifiers",
                "metadata"
              ],
              "": [
                "ast"
              ]
            }
          }
        }
      },
      "imports": [],
      "versionPragmas": [
        "^0.8.24"
      ],
      "artifacts": [
        "EventLogger"
      ]
    },
    "/home/runner/work/solidity-notebook/solidity-notebook/contracts/utils/EventLogger_1767857040.sol": {
      "lastModificationDate": 1768087978235,
      "contentHash": "261c7e8eced1c852b3ea6fd3f1bf851c",
      "sourceName": "contracts/utils/EventLogger_1767857040.sol",
      "solcConfig": {
        "version": "0.8.24",
        "settings": {
          "optimizer": {
            "enabled": true,
            "runs": 200
          },
          "evmVersion": "paris",
          "outputSelection": {
            "*": {
              "*": [
                "abi",
                "evm.bytecode",
                "evm.deployedBytecode",
                "evm.methodIdentifiers",
                "metadata"
              ],
              "": [
                "ast"
              ]
            }
          }
        }
      },
      "imports": [],
      "versionPragmas": [
        "^0.8.24"
      ],
      "artifacts": [
        "EventLogger"
      ]
    },
    "/home/runner/work/solidity-notebook/solidity-notebook/contracts/utils/EventLogger_1767901934.sol": {
      "lastModificationDate": 1768087978235,
      "contentHash": "261c7e8eced1c852b3ea6fd3f1bf851c",
      "sourceName": "contracts/utils/EventLogger_1767901934.sol",
      "solcConfig": {
        "version": "0.8.24",
        "settings": {
          "optimizer": {
            "enabled": true,
            "runs": 200
          },
          "evmVersion": "paris",
          "outputSelection": {
            "*": {
              "*": [
                "abi",
                "evm.bytecode",
                "evm.deployedBytecode",
                "evm.methodIdentifiers",
                "metadata"
              ],
              "": [
                "ast"
              ]
            }
          }
        }
      },
      "imports": [],
      "versionPragmas": [
        "^0.8.24"
      ],
      "artifacts": [
        "EventLogger"
      ]
    },
    "/home/runner/work/solidity-notebook/solidity-notebook/contracts/utils/EventLogger_1767905685.sol": {
      "lastModificationDate": 1768087978235,
      "contentHash": "261c7e8eced1c852b3ea6fd3f1bf851c",
      "sourceName": "contracts/utils/EventLogger_1767905685.sol",
      "solcConfig": {
        "version": "0.8.24",
        "settings": {
          "optimizer": {
            "enabled": true,
            "runs": 200
          },
          "evmVersion": "paris",
          "outputSelection": {
            "*": {
              "*": [
                "abi",
                "evm.bytecode",
                "evm.deployedBytecode",
                "evm.methodIdentifiers",
                "metadata"
              ],
              "": [
                "ast"
              ]
            }
          }
        }
      },
      "imports": [],
      "versionPragmas": [
        "^0.8.24"
      ],
      "artifacts": [
        "EventLogger"
      ]
    },
    "/home/runner/work/solidity-notebook/solidity-notebook/contracts/utils/EventLogger_1767938428.sol": {
      "lastModificationDate": 1768087978235,
      "contentHash": "261c7e8eced1c852b3ea6fd3f1bf851c",
      "sourceName": "contracts/utils/EventLogger_1767938428.sol",
      "solcConfig": {
        "version": "0.8.24",
        "settings": {
          "optimizer": {
            "enabled": true,
            "runs": 200
          },
          "evmVersion": "paris",
          "outputSelection": {
            "*": {
              "*": [
                "abi",
                "evm.bytecode",
                "evm.deployedBytecode",
                "evm.methodIdentifiers",
                "metadata"
              ],
              "": [
                "ast"
              ]
            }
          }
        }
      },
      "imports": [],
      "versionPragmas": [
        "^0.8.24"
      ],
      "artifacts": [
        "EventLogger"
      ]
    },
    "/home/runner/work/solidity-notebook/solidity-notebook/contracts/utils/EventLogger_1767981515.sol": {
      "lastModificationDate": 1768087978235,
      "contentHash": "261c7e8eced1c852b3ea6fd3f1bf851c",
      "sourceName": "contracts/utils/EventLogger_1767981515.sol",
      "solcConfig": {
        "version": "0.8.24",
        "settings": {
          "optimizer": {
            "enabled": true,
            "runs": 200
          },
          "evmVersion": "paris",
          "outputSelection": {
            "*": {
              "*": [
                "abi",
                "evm.bytecode",
                "evm.deployedBytecode",
                "evm.methodIdentifiers",
                "metadata"
              ],
              "": [
                "ast"
              ]
            }
          }
        }
      },
      "imports": [],
      "versionPragmas": [
        "^0.8.24"
      ],
      "artifacts": [
        "EventLogger"
      ]
    },
    "/home/runner/work/solidity-notebook/solidity-notebook/contracts/utils/EventLogger_1767997268.sol": {
      "lastModificationDate": 1768087978235,
      "contentHash": "261c7e8eced1c852b3ea6fd3f1bf851c",
      "sourceName": "contracts/utils/EventLogger_1767997268.sol",
      "solcConfig": {
        "version": "0.8.24",
        "settings": {
          "optimizer": {
            "enabled": true,
            "runs": 200
          },
          "evmVersion": "paris",
          "outputSelection": {
            "*": {
              "*": [
                "abi",
                "evm.bytecode",
                "evm.deployedBytecode",
                "evm.methodIdentifiers",
                "metadata"
              ],
              "": [
                "ast"
              ]
            }
          }
        }
      },
      "imports": [],
      "versionPragmas": [
        "^0.8.24"
      ],
      "artifacts": [
        "EventLogger"
      ]
    },
    "/home/runner/work/solidity-notebook/solidity-notebook/contracts/utils/EventLogger_1768017381.sol": {
      "lastModificationDate": 1768087978235,
      "contentHash": "261c7e8eced1c852b3ea6fd3f1bf851c",
      "sourceName": "contracts/utils/EventLogger_1768017381.sol",
      "solcConfig": {
        "version": "0.8.24",
        "settings": {
          "optimizer": {
            "enabled": true,
            "runs": 200
          },
          "evmVersion": "paris",
          "outputSelection": {
            "*": {
              "*": [
                "abi",
                "evm.bytecode",
                "evm.deployedBytecode",
                "evm.methodIdentifiers",
                "metadata"
              ],
              "": [
                "ast"
              ]
            }
          }
        }
      },
      "imports": [],
      "versionPragmas": [
        "^0.8.24"
      ],
      "artifacts": [
        "EventLogger"
      ]
    },
    "/home/runner/work/solidity-notebook/solidity-notebook/contracts/utils/EventLogger_1768028390.sol": {
      "lastModificationDate": 1768087978235,
      "contentHash": "261c7e8eced1c852b3ea6fd3f1bf851c",
      "sourceName": "contracts/utils/EventLogger_1768028390.sol",
      "solcConfig": {
        "version": "0.8.24",
        "settings": {
          "optimizer": {
            "enabled": true,
            "runs": 200
          },
          "evmVersion": "paris",
          "outputSelection": {
            "*": {
              "*": [
                "abi",
                "evm.bytecode",
                "evm.deployedBytecode",
                "evm.methodIdentifiers",
                "metadata"
              ],
              "": [
                "ast"
              ]
            }
          }
        }
      },
      "imports": [],
      "versionPragmas": [
        "^0.8.24"
      ],
      "artifacts": [
        "EventLogger"
      ]
    },
    "/home/runner/work/solidity-notebook/solidity-notebook/contracts/utils/EventLogger_1768029575.sol": {
      "lastModificationDate": 1768087978235,
      "contentHash": "261c7e8eced1c852b3ea6fd3f1bf851c",
      "sourceName": "contracts/utils/EventLogger_1768029575.sol",
      "solcConfig": {
        "version": "0.8.24",
        "settings": {
          "optimizer": {
            "enabled": true,
            "runs": 200
          },
          "evmVersion": "paris",
          "outputSelection": {
            "*": {
              "*": [
                "abi",
                "evm.bytecode",
                "evm.deployedBytecode",
                "evm.methodIdentifiers",
                "metadata"
              ],
              "": [
                "ast"
              ]
            }
          }
        }
      },
      "imports": [],
      "versionPragmas": [
        "^0.8.24"
      ],
      "artifacts": [
        "EventLogger"
      ]
    },
    "/home/runner/work/solidity-notebook/solidity-notebook/contracts/utils/EventLogger_1768038779.sol": {
      "lastModificationDate": 1768087978235,
      "contentHash": "261c7e8eced1c852b3ea6fd3f1bf851c",
      "sourceName": "contracts/utils/EventLogger_1768038779.sol",
      "solcConfig": {
        "version": "0.8.24",
        "settings": {
          "optimizer": {
            "enabled": true,
            "runs": 200
          },
          "evmVersion": "paris",
          "outputSelection": {
            "*": {
              "*": [
                "abi",
                "evm.bytecode",
                "evm.deployedBytecode",
                "evm.methodIdentifiers",
                "metadata"
              ],
              "": [
                "ast"
              ]
            }
          }
        }
      },
      "imports": [],
      "versionPragmas": [
        "^0.8.24"
      ],
      "artifacts": [
        "EventLogger"
      ]
    },
    "/home/runner/work/solidity-notebook/solidity-notebook/contracts/utils/EventLogger_1768051969.sol": {
      "lastModificationDate": 1768087978235,
      "contentHash": "261c7e8eced1c852b3ea6fd3f1bf851c",
      "sourceName": "contracts/utils/EventLogger_1768051969.sol",
      "solcConfig": {
        "version": "0.8.24",
        "settings": {
          "optimizer": {
            "enabled": true,
            "runs": 200
          },
          "evmVersion": "paris",
          "outputSelection": {
            "*": {
              "*": [
                "abi",
                "evm.bytecode",
                "evm.deployedBytecode",
                "evm.methodIdentifiers",
                "metadata"
              ],
              "": [
                "ast"
              ]
            }
          }
        }
      },
      "imports": [],
      "versionPragmas": [
        "^0.8.24"
      ],
      "artifacts": [
        "EventLogger"
      ]
    },
    "/home/runner/work/solidity-notebook/solidity-notebook/contracts/utils/EventLogger_1768054837.sol": {
      "lastModificationDate": 1768087978235,
      "contentHash": "261c7e8eced1c852b3ea6fd3f1bf851c",
      "sourceName": "contracts/utils/EventLogger_1768054837.sol",
      "solcConfig": {
        "version": "0.8.24",
        "settings": {
          "optimizer": {
            "enabled": true,
            "runs": 200
          },
          "evmVersion": "paris",
          "outputSelection": {
            "*": {
              "*": [
                "abi",
                "evm.bytecode",
                "evm.deployedBytecode",
                "evm.methodIdentifiers",
                "metadata"
              ],
              "": [
                "ast"
              ]
            }
          }
        }
      },
      "imports": [],
      "versionPragmas": [
        "^0.8.24"
      ],
      "artifacts": [
        "EventLogger"
      ]
    },
    "/home/runner/work/solidity-notebook/solidity-notebook/contracts/utils/EventLogger_1768060633.sol": {
      "lastModificationDate": 1768087978235,
      "contentHash": "261c7e8eced1c852b3ea6fd3f1bf851c",
      "sourceName": "contracts/utils/EventLogger_1768060633.sol",
      "solcConfig": {
        "version": "0.8.24",
        "settings": {
          "optimizer": {
            "enabled": true,
            "runs": 200
          },
          "evmVersion": "paris",
          "outputSelection": {
            "*": {
              "*": [
                "abi",
                "evm.bytecode",
                "evm.deployedBytecode",
                "evm.methodIdentifiers",
                "metadata"
              ],
              "": [
                "ast"
              ]
            }
          }
        }
      },
      "imports": [],
      "versionPragmas": [
        "^0.8.24"
      ],
      "artifacts": [
        "EventLogger"
      ]
    },
    "/home/runner/work/solidity-notebook/solidity-notebook/contracts/utils/EventLogger_1768071500.sol": {
      "lastModificationDate": 1768087978235,
      "contentHash": "261c7e8eced1c852b3ea6fd3f1bf851c",
      "sourceName": "contracts/utils/EventLogger_1768071500.sol",
      "solcConfig": {
        "version": "0.8.24",
        "settings": {
          "optimizer": {
            "enabled": true,
            "runs": 200
          },
          "evmVersion": "paris",
          "outputSelection": {
            "*": {
              "*": [
                "abi",
                "evm.bytecode",
                "evm.deployedBytecode",
                "evm.methodIdentifiers",
                "metadata"
              ],
              "": [
                "ast"
              ]
            }
          }
        }
      },
      "imports": [],
      "versionPragmas": [
        "^0.8.24"
      ],
      "artifacts": [
        "EventLogger"
      ]
    },
    "/home/runner/work/solidity-notebook/solidity-notebook/contracts/utils/EventLogger_1768078180.sol": {
      "lastModificationDate": 1768087978235,
      "contentHash": "261c7e8eced1c852b3ea6fd3f1bf851c",
      "sourceName": "contracts/utils/EventLogger_1768078180.sol",
      "solcConfig": {
        "version": "0.8.24",
        "settings": {
          "optimizer": {
            "enabled": true,
            "runs": 200
          },
          "evmVersion": "paris",
          "outputSelection": {
            "*": {
              "*": [
                "abi",
                "evm.bytecode",
                "evm.deployedBytecode",
                "evm.methodIdentifiers",
                "metadata"
              ],
              "": [
                "ast"
              ]
            }
          }
        }
      },
      "imports": [],
      "versionPragmas": [
        "^0.8.24"
      ],
      "artifacts": [
        "EventLogger"
      ]
    },
    "/home/runner/work/solidity-notebook/solidity-notebook/contracts/utils/EventLogger_1768078549.sol": {
      "lastModificationDate": 1768087978235,
      "contentHash": "261c7e8eced1c852b3ea6fd3f1bf851c",
      "sourceName": "contracts/utils/EventLogger_1768078549.sol",
      "solcConfig": {
        "version": "0.8.24",
        "settings": {
          "optimizer": {
            "enabled": true,
            "runs": 200
          },
          "evmVersion": "paris",
          "outputSelection": {
            "*": {
              "*": [
                "abi",
                "evm.bytecode",
                "evm.deployedBytecode",
                "evm.methodIdentifiers",
                "metadata"
              ],
              "": [
                "ast"
              ]
            }
          }
        }
      },
      "imports": [],
      "versionPragmas": [
        "^0.8.24"
      ],
      "artifacts": [
        "EventLogger"
      ]
    },
    "/home/runner/work/solidity-notebook/solidity-notebook/contracts/utils/EventLogger_1768081117.sol": {
      "lastModificationDate": 1768087978236,
      "contentHash": "261c7e8eced1c852b3ea6fd3f1bf851c",
      "sourceName": "contracts/utils/EventLogger_1768081117.sol",
      "solcConfig": {
        "version": "0.8.24",
        "settings": {
          "optimizer": {
            "enabled": true,
            "runs": 200
          },
          "evmVersion": "paris",
          "outputSelection": {
            "*": {
              "*": [
                "abi",
                "evm.bytecode",
                "evm.deployedBytecode",
                "evm.methodIdentifiers",
                "metadata"
              ],
              "": [
                "ast"
              ]
            }
          }
        }
      },
      "imports": [],
      "versionPragmas": [
        "^0.8.24"
      ],
      "artifacts": [
        "EventLogger"
      ]
    }
  }
}
